{
  "project_info": {
    "project_number": "172157626367",
    "project_id": "employ-ededc",
    "storage_bucket": "employ-ededc.appspot.com"
  },
  "client": [
    {
      "client_info": {
        "mobilesdk_app_id": "1:172157626367:android:a8788d9820bd72e94329ca",
        "android_client_info": {
          "package_name": "com.example.employ"
        }
      },
      "oauth_client": [],
      "api_key": [
        {
          "current_key": "AIzaSyALHf6Dl4iXAGyESj7gZYbGIFI6E9O8Iik"
        }
      ],
      "services": {
        "appinvite_service": {
          "other_platform_oauth_client": []
        }
      }
    },
    {
      "client_info": {
        "mobilesdk_app_id": "1:172157626367:android:0e95ade2758e07124329ca",
        "android_client_info": {
          "package_name": "com.example.employee_app"
        }
      },
      "oauth_client": [],
      "api_key": [
        {
          "current_key": "AIzaSyALHf6Dl4iXAGyESj7gZYbGIFI6E9O8Iik"
        }
      ],
      "services": {
        "appinvite_service": {
          "other_platform_oauth_client": []
        }
      }
    },
    {
      "client_info": {
        "mobilesdk_app_id": "1:172157626367:android:d6c5a51e4e24408e4329ca",
        "android_client_info": {
          "package_name": "com.example.empolyee_app"
        }
      },
      "oauth_client": [],
      "api_key": [
        {
          "current_key": "AIzaSyALHf6Dl4iXAGyESj7gZYbGIFI6E9O8Iik"
        }
      ],
      "services": {
        "appinvite_service": {
          "other_platform_oauth_client": []
        }
      }
    }
  ],
  "configuration_version": "1"
}